exasol_transformers_extension/__init__.py
exasol_transformers_extension/deploy.py
exasol_transformers_extension/deployment/__init__.py
exasol_transformers_extension/deployment/constants.py
exasol_transformers_extension/deployment/deployment_utils.py
exasol_transformers_extension/deployment/install_scripts_constants.py
exasol_transformers_extension/deployment/language_container.py
exasol_transformers_extension/deployment/scripts_deployer.py
exasol_transformers_extension/deployment/te_language_container_deployer.py
exasol_transformers_extension/deployment/work_with_spans_constants.py
exasol_transformers_extension/deployment/work_without_spans_constants.py
exasol_transformers_extension/resources/__init__.py
exasol_transformers_extension/resources/templates/delete_model_udf.jinja.sql
exasol_transformers_extension/resources/templates/filling_mask_udf.jinja.sql
exasol_transformers_extension/resources/templates/ls_models_udf.jinja.sql
exasol_transformers_extension/resources/templates/model_downloader_udf.jinja.sql
exasol_transformers_extension/resources/templates/question_answering_udf.jinja.sql
exasol_transformers_extension/resources/templates/sequence_classification_single_text_udf.jinja.sql
exasol_transformers_extension/resources/templates/sequence_classification_text_pair_udf.jinja.sql
exasol_transformers_extension/resources/templates/text_generation_udf.jinja.sql
exasol_transformers_extension/resources/templates/translation_udf.jinja.sql
exasol_transformers_extension/resources/templates/with_spans/span_token_classification_udf.jinja.sql
exasol_transformers_extension/resources/templates/with_spans/span_zero_shot_text_classification_udf.jinja.sql
exasol_transformers_extension/resources/templates/without_spans/token_classification_udf.jinja.sql
exasol_transformers_extension/resources/templates/without_spans/zero_shot_text_classification_udf.jinja.sql
exasol_transformers_extension/udfs/__init__.py
exasol_transformers_extension/udfs/callers/__init__.py
exasol_transformers_extension-3.0.0.dist-info/LICENSE
exasol_transformers_extension-3.0.0.dist-info/METADATA
exasol_transformers_extension-3.0.0.dist-info/WHEEL
exasol_transformers_extension-3.0.0.dist-info/RECORD
