Metadata-Version: 2.3
Name: exasol-transformers-extension
Version: 3.0.0
Summary: An Exasol extension for using state-of-the-art pretrained machine learning models via the Hugging Face Transformers API.
Keywords: exasol
Author: Umit Buyuksahin
Author-email: umit.buyuksahin@exasol.com
Requires-Python: >=3.10.0,<3.15
Classifier: Programming Language :: Python :: 3
Classifier: Programming Language :: Python :: 3.10
Classifier: Programming Language :: Python :: 3.11
Classifier: Programming Language :: Python :: 3.12
Classifier: Programming Language :: Python :: 3.13
Requires-Dist: Jinja2 (>=3.1.6,<4.0.0)
Requires-Dist: bitsandbytes (>=0.45.0)
Requires-Dist: click (>=8.0.4,<9.0.0)
Requires-Dist: exasol-bucketfs (>=1.0.0)
Requires-Dist: exasol-python-extension-common (>=0.9.0,<1)
Requires-Dist: importlib-resources (>=6.4.0,<7.0.0)
Requires-Dist: numpy (<=1.26.4)
Requires-Dist: pandas (>=2.2.3,<3.0.0)
Requires-Dist: pyexasol (>=0.25.0,<2)
Requires-Dist: sacremoses (>=0.0.53)
Requires-Dist: tenacity (>=8.2.2,<9.0.0)
Requires-Dist: torch (>=2.8.0,<3.0.0)
Requires-Dist: transformers[torch] (>=4.36.2,<5.0.0)
Project-URL: Homepage, https://github.com/exasol/transformers-extension
Project-URL: Repository, https://github.com/exasol/transformers-extension
